deamons_fridrich_connection-0.0.1-py3.10-nspkg.pth
deamons/fridrich_connection/__init__.py
deamons_fridrich_connection-0.0.1.dist-info/LICENSE
deamons_fridrich_connection-0.0.1.dist-info/METADATA
deamons_fridrich_connection-0.0.1.dist-info/WHEEL
deamons_fridrich_connection-0.0.1.dist-info/namespace_packages.txt
deamons_fridrich_connection-0.0.1.dist-info/top_level.txt
deamons_fridrich_connection-0.0.1.dist-info/RECORD
